expetator/__init__.py
expetator/experiment.py
expetator/tools.py
expetator/benchmarks/NPB3.4-MPI.tgz
expetator/benchmarks/__init__.py
expetator/benchmarks/cpu.c
expetator/benchmarks/cpubench.py
expetator/benchmarks/gpucpubench.py
expetator/benchmarks/gpumembench.py
expetator/benchmarks/gromacsBFC.tpr
expetator/benchmarks/gromacsMEM.tpr
expetator/benchmarks/gromacsbench.py
expetator/benchmarks/m.cu
expetator/benchmarks/mem.c
expetator/benchmarks/membench.py
expetator/benchmarks/mpi_generic.c
expetator/benchmarks/mpibench.py
expetator/benchmarks/npbbench.py
expetator/benchmarks/percentage_load.c
expetator/benchmarks/percentagebench.py
expetator/benchmarks/sleepbench.py
expetator/leverages/__init__.py
expetator/leverages/dvfs.py
expetator/leverages/dvfs_pct.sh
expetator/leverages/gpuclock.py
expetator/leverages/gpupow.py
expetator/leverages/neosched.py
expetator/leverages/neosched_lib.h
expetator/leverages/neosched_main.c
expetator/leverages/neosched_mak
expetator/leverages/neosched_skel.c
expetator/leverages/pct.py
expetator/leverages/template.py
expetator/monitors/__init__.py
expetator/monitors/laptop_power_monitor.py
expetator/monitors/mojitos.py
expetator/monitors/power.py
expetator/monitors/powergpu.py
expetator_gdacosta-0.0.2.dist-info/LICENSE
expetator_gdacosta-0.0.2.dist-info/METADATA
expetator_gdacosta-0.0.2.dist-info/WHEEL
expetator_gdacosta-0.0.2.dist-info/top_level.txt
expetator_gdacosta-0.0.2.dist-info/RECORD
