Metadata-Version: 2.1
Name: expetator-gdacosta
Version: 0.0.2
Summary: A framework for monitoring HPC applications using DVFS
Home-page: https://github.com/georges-da-costa/expetator
Author: Georges Da Costa
Author-email: georges.da-costa@irit.fr
License: UNKNOWN
Platform: UNKNOWN
Classifier: Programming Language :: Python :: 3
Classifier: License :: OSI Approved :: GNU General Public License v3 or later (GPLv3+)
Classifier: Operating System :: OS Independent
Requires-Python: >=3.6
